README.md
setup.py
simular-stubs/__init__.pyi
simular-stubs/contract.pyi
simular-stubs/simular.pyi
simular-stubs/utils.pyi
simular_eth_stubs.egg-info/PKG-INFO
simular_eth_stubs.egg-info/SOURCES.txt
simular_eth_stubs.egg-info/dependency_links.txt
simular_eth_stubs.egg-info/top_level.txt