Metadata-Version: 2.1
Name: simular-eth-stubs
Version: 0.0.7
Summary: Type stubs for simular-evm
Home-page: https://github.com/james4ever0/simular-evm-stubs
License: UNKNOWN
Platform: UNKNOWN
